docker_mcp/__init__.py
docker_mcp/docker_executor.py
docker_mcp/handlers.py
docker_mcp/server.py
docker_mcp-0.2.0.dist-info/METADATA
docker_mcp-0.2.0.dist-info/WHEEL
docker_mcp-0.2.0.dist-info/entry_points.txt
docker_mcp-0.2.0.dist-info/licenses/LICENSE
docker_mcp-0.2.0.dist-info/RECORD
