Metadata-Version: 2.3
Name: docker-mcp
Version: 0.2.0
Summary: A docker MCP server
Author-email: Alex Andru <alex007d@gmail.com>
Requires-Python: >=3.12
Requires-Dist: httpx>=0.28.0
Requires-Dist: mcp>=1.0.0
Requires-Dist: python-dotenv>=1.0.1
Requires-Dist: python-on-whales>=0.67.0
Requires-Dist: pyyaml>=6.0.1
